py_docx_creator/AbstractClasses.py
py_docx_creator/CoreClasses.py
py_docx_creator/CustomClasses.py
py_docx_creator/__init__.py
py_docx_creator-0.1.4.5.dist-info/METADATA
py_docx_creator-0.1.4.5.dist-info/WHEEL
py_docx_creator-0.1.4.5.dist-info/top_level.txt
py_docx_creator-0.1.4.5.dist-info/RECORD
