Metadata-Version: 2.4
Name: py_docx_creator
Version: 0.1.4.5
Summary: Пакет для работы с .docx файлами
Author-email: Nikolay <kola8911764@gmail.com>
License: MIT
Project-URL: Homepage, https://github.com/HitsukaRgb/py_docx_creator/
Requires-Python: >=3.12
Requires-Dist: python-docx
